setup.py
bosh_db2bt.egg-info/PKG-INFO
bosh_db2bt.egg-info/SOURCES.txt
bosh_db2bt.egg-info/dependency_links.txt
bosh_db2bt.egg-info/not-zip-safe
bosh_db2bt.egg-info/requires.txt
bosh_db2bt.egg-info/top_level.txt
db2bt/__init__.py
db2bt/mysql2bt.py