Metadata-Version: 1.0
Name: bosh-db2bt
Version: 0.0.5
Summary: copy mysql/postgresql tables to BigObject server
Home-page: https://github.com/macrodatalab/db2bt.git
Author: MacroData Inc
Author-email: info@macrodatalab.com
License: Apache 2.0
Keywords: bigobject,macrodata,database,command line tool,mysql,postgresql
Platform: UNKNOWN
